agentlib_mpc/__init__.py
agentlib_mpc/data_structures/__init__.py
agentlib_mpc/data_structures/admm_datatypes.py
agentlib_mpc/data_structures/casadi_utils.py
agentlib_mpc/data_structures/coordinator_datatypes.py
agentlib_mpc/data_structures/interpolation.py
agentlib_mpc/data_structures/ml_model_datatypes.py
agentlib_mpc/data_structures/mpc_datamodels.py
agentlib_mpc/models/__init__.py
agentlib_mpc/models/casadi_ml_model.py
agentlib_mpc/models/casadi_model.py
agentlib_mpc/models/casadi_predictor.py
agentlib_mpc/models/serialized_ml_model.py
agentlib_mpc/modules/__init__.py
agentlib_mpc/modules/data_source.py
agentlib_mpc/modules/minlp_mpc.py
agentlib_mpc/modules/ml_model_simulator.py
agentlib_mpc/modules/mpc.py
agentlib_mpc/modules/mpc_full.py
agentlib_mpc/modules/InputPrediction/__init__.py
agentlib_mpc/modules/InputPrediction/try_predictor.py
agentlib_mpc/modules/dmpc/__init__.py
agentlib_mpc/modules/dmpc/coordinator.py
agentlib_mpc/modules/dmpc/employee.py
agentlib_mpc/modules/dmpc/admm/__init__.py
agentlib_mpc/modules/dmpc/admm/admm.py
agentlib_mpc/modules/dmpc/admm/admm_coordinated.py
agentlib_mpc/modules/dmpc/admm/admm_coordinator.py
agentlib_mpc/modules/estimation/__init__.py
agentlib_mpc/modules/estimation/mhe.py
agentlib_mpc/modules/ml_model_training/__init__.py
agentlib_mpc/modules/ml_model_training/data_reduction.py
agentlib_mpc/modules/ml_model_training/ml_model_trainer.py
agentlib_mpc/modules/ml_model_training/setpoint_generator.py
agentlib_mpc/optimization_backends/README.md
agentlib_mpc/optimization_backends/__init__.py
agentlib_mpc/optimization_backends/backend.py
agentlib_mpc/optimization_backends/casadi_/__init__.py
agentlib_mpc/optimization_backends/casadi_/admm.py
agentlib_mpc/optimization_backends/casadi_/basic.py
agentlib_mpc/optimization_backends/casadi_/casadi_admm_ml.py
agentlib_mpc/optimization_backends/casadi_/casadi_ml.py
agentlib_mpc/optimization_backends/casadi_/full.py
agentlib_mpc/optimization_backends/casadi_/mhe.py
agentlib_mpc-0.6.4.dist-info/LICENSE
agentlib_mpc-0.6.4.dist-info/METADATA
agentlib_mpc-0.6.4.dist-info/WHEEL
agentlib_mpc-0.6.4.dist-info/top_level.txt
agentlib_mpc-0.6.4.dist-info/RECORD
