Metadata-Version: 2.1
Name: agentlib_mpc
Version: 0.6.4
Summary: Framework for development and execution of agents for control and simulation of energy systems.
Author-email: Associates of the AGENT project <AGENT.Projekt@eonerc.rwth-aachen.de>
License: BSD-3-Clause
Keywords: agents,mpc,control,distributed
Classifier: Programming Language :: Python :: 3.9
Classifier: Programming Language :: Python :: 3.10
Classifier: Programming Language :: Python :: 3.11
Classifier: Programming Language :: Python :: 3.12
Requires-Python: >=3.9
License-File: LICENSE
Requires-Dist: numpy<2.0,>=1.17.4
Requires-Dist: pandas>=1.1.0
Requires-Dist: scipy>=1.5.2
Requires-Dist: simpy>=4.0.1
Requires-Dist: pydantic>=2.0.0
Requires-Dist: casadi>=3.6.6
Requires-Dist: matplotlib>=3.5.1
Requires-Dist: matplotlib
Requires-Dist: attrs>=22.2.0
Requires-Dist: agentlib>=0.6.0
Requires-Dist: orjson>=3.9.5
Requires-Dist: rapidfuzz>=1.7.0
Requires-Dist: agentlib>=0.8.0
Provides-Extra: fmu
Requires-Dist: FMPy>=0.3.6; extra == "fmu"
Provides-Extra: ml
Requires-Dist: keras>=2.6.0; extra == "ml"
Requires-Dist: tensorflow>=2.6.0; extra == "ml"
Requires-Dist: scikit-learn; extra == "ml"
Provides-Extra: interactive
Requires-Dist: plotly>=5.20.0; extra == "interactive"
Requires-Dist: dash>=2.16.1; extra == "interactive"
Requires-Dist: dash_daq; extra == "interactive"
Provides-Extra: full
Requires-Dist: agentlib_mpc[fmu,interactive,ml]; extra == "full"
Requires-Dist: agentlib[full]; extra == "full"
